parallel_hierarchy/__init__.py
parallel_hierarchy/_version.py
parallel_hierarchy/py.typed
python_parallel_hierarchy-0.7.1.dist-info/LICENSE
python_parallel_hierarchy-0.7.1.dist-info/METADATA
python_parallel_hierarchy-0.7.1.dist-info/WHEEL
python_parallel_hierarchy-0.7.1.dist-info/top_level.txt
python_parallel_hierarchy-0.7.1.dist-info/RECORD
