Metadata-Version: 2.1
Name: python-parallel-hierarchy
Version: 0.7.1
Summary: A utility for creating a parallel class hierarchy based on a primary set of classes.
Author-email: Joël Larose <joel.larose@gmail.com>
License: Apache License
Project-URL: Repository, https://gitlab.com/joel.larose/python-parallel-hierarchy
Project-URL: Issue Tracker, https://gitlab.com/joel.larose/python-parallel-hierarchy/-/issues
Keywords: metaprogramming,class hierarchy,don't repeat yourself,DRY
Classifier: Development Status :: 4 - Beta
Classifier: License :: OSI Approved :: Apache Software License
Classifier: Operating System :: OS Independent
Classifier: Programming Language :: Python :: 3
Classifier: Programming Language :: Python :: 3.9
Classifier: Programming Language :: Python :: 3.10
Classifier: Topic :: Software Development :: Code Generators
Classifier: Topic :: Software Development :: Libraries
Classifier: Topic :: Utilities
Classifier: Typing :: Typed
Classifier: Intended Audience :: Developers
Requires-Python: >=3.9
License-File: LICENSE
Provides-Extra: all
Requires-Dist: python-parallel-hierarchy[docs,lintcheck,test,typecheck] ; extra == 'all'
Provides-Extra: docs
Requires-Dist: Sphinx ; extra == 'docs'
Requires-Dist: sphinx-git ; extra == 'docs'
Requires-Dist: sphinxcontrib-plantuml ; extra == 'docs'
Provides-Extra: lintcheck
Requires-Dist: pylint ; extra == 'lintcheck'
Requires-Dist: pylint-venv ; extra == 'lintcheck'
Requires-Dist: pylint-pytest ; extra == 'lintcheck'
Provides-Extra: test
Requires-Dist: pytest ; extra == 'test'
Requires-Dist: pytest-cov ; extra == 'test'
Provides-Extra: typecheck
Requires-Dist: mypy ; extra == 'typecheck'
